tera_tera/__init__.py
tera_tera/__main__.py
tera_tera/cli.py
tera_tera/assets/bangalore-gurudwara.jpg
tera_tera/assets/data-bandi-chor-gurudwara-gwalior.JPG
tera_tera/assets/dhandhanbabadeep-singh-gurudwara lah sah.JPG
tera_tera/assets/gurudwara-gawrikat-jabalpur.JPG
tera_tera/assets/gurukataal-agra.JPG
tera_tera/assets/harmandir-sahib-amritsar.JPG
tera_tera-0.1.1.dist-info/licenses/LICENSE
tera_tera-0.1.1.dist-info/METADATA
tera_tera-0.1.1.dist-info/WHEEL
tera_tera-0.1.1.dist-info/entry_points.txt
tera_tera-0.1.1.dist-info/top_level.txt
tera_tera-0.1.1.dist-info/RECORD
