Metadata-Version: 2.4
Name: tera-tera
Version: 0.1.1
Summary: Tera tera app to do langar seva at various gurudwara's
Author: Sukhbinder Singh
License: Apache-2.0
Project-URL: Homepage, https://github.com/sukhbinder/tera-tera
Project-URL: Changelog, https://github.com/sukhbinder/tera-tera/releases
Project-URL: Issues, https://github.com/sukhbinder/tera-tera/issues
Project-URL: CI, https://github.com/sukhbinder/tera-tera/actions
Classifier: License :: OSI Approved :: Apache Software License
Requires-Python: >=3.8
License-File: LICENSE
Provides-Extra: test
Requires-Dist: pytest; extra == "test"
Dynamic: license-file
